iosslsniffer/__init__.py
iosslsniffer/__main__.py
iosslsniffer/exceptions.py
iosslsniffer/sniffer.py
iosslsniffer/ssl_session.py
iosslsniffer/syslog_parser.py
iosslsniffer/tcp_simulation.py
iosslsniffer-0.0.2.dist-info/METADATA
iosslsniffer-0.0.2.dist-info/WHEEL
iosslsniffer-0.0.2.dist-info/entry_points.txt
iosslsniffer-0.0.2.dist-info/top_level.txt
iosslsniffer-0.0.2.dist-info/RECORD
