Metadata-Version: 2.1
Name: iosslsniffer
Version: 0.0.2
Summary: Sniffer for encrypted traffic
Author-email: netanelc305 <netanelc305@protonmail.com>, doronz88 <doron88@gmail.com>
Maintainer-email: netanelc305 <netanelc305@protonmail.com>, doronz88 <doron88@gmail.com>
Project-URL: Homepage, https://github.com/netanelc305/ioSSLsniffer
Project-URL: Bug Reports, https://github.com/netanelc305/ioSSLsniffer/issues
Keywords: ios,jailbreak,ssl,sniffer,tls,cli,automation
Classifier: Operating System :: iOS
Classifier: Development Status :: 5 - Production/Stable
Classifier: License :: OSI Approved :: GNU General Public License v3 or later (GPLv3+)
Classifier: Programming Language :: Python :: 3
Classifier: Programming Language :: Python :: 3.8
Classifier: Programming Language :: Python :: 3.9
Classifier: Programming Language :: Python :: 3.10
Classifier: Programming Language :: Python :: 3.11
Classifier: Programming Language :: Python :: 3 :: Only
Requires-Python: >=3.8
Requires-Dist: pymobiledevice3 (>=2.1.0)
Requires-Dist: click (>=8.1.3)
Requires-Dist: scapy (>=2.5.0)
Requires-Dist: parse (>=1.19.0)
Requires-Dist: coloredlogs (>=15.0.1)
Requires-Dist: rpcclient (>=3.16.0)
Provides-Extra: test
Requires-Dist: pytest ; extra == 'test'
